weather_forecast_retrieval/__init__.py
weather_forecast_retrieval/grib2nc.py
weather_forecast_retrieval/hrrr.py
weather_forecast_retrieval/hrrr_archive.py
weather_forecast_retrieval/rap.py
weather_forecast_retrieval/utils.py
weather_forecast_retrieval-0.6.14.data/scripts/convert_grib2nc
weather_forecast_retrieval-0.6.14.data/scripts/run_hrrr_retrieval
weather_forecast_retrieval-0.6.14.data/scripts/run_hrrr_retrieval_dates
weather_forecast_retrieval-0.6.14.dist-info/AUTHORS.rst
weather_forecast_retrieval-0.6.14.dist-info/LICENSE
weather_forecast_retrieval-0.6.14.dist-info/METADATA
weather_forecast_retrieval-0.6.14.dist-info/WHEEL
weather_forecast_retrieval-0.6.14.dist-info/entry_points.txt
weather_forecast_retrieval-0.6.14.dist-info/top_level.txt
weather_forecast_retrieval-0.6.14.dist-info/RECORD
