Metadata-Version: 2.1
Name: weather-forecast-retrieval
Version: 0.6.14
Summary: Weather forecast retrieval gathers relevant gridded weather forecasts to ingest into physically based models for water supply forecasts
Home-page: https://github.com/USDA-ARS-NWRC/weather_forecast_retrieval
Author: Scott Havens
Author-email: scott.havens@ars.usda.gov
License: CC0 1.0
Keywords: weather_forecast_retrieval
Platform: UNKNOWN
Classifier: Development Status :: 4 - Beta
Classifier: Intended Audience :: Developers
Classifier: Natural Language :: English
Classifier: Programming Language :: Python :: 3.6
Classifier: Programming Language :: Python :: 3.7
Requires-Dist: coloredlogs
Requires-Dist: siphon (>=0.6.1)
Requires-Dist: utm (==0.4.0)
Requires-Dist: pytz
Requires-Dist: requests (>=2.21.0)
Requires-Dist: netCDF4 (>=1.5.1.2)
Requires-Dist: xarray (>=0.15.0)
Requires-Dist: cfgrib (>=0.9.7.1)
Requires-Dist: beautifulsoup4
Requires-Dist: pandas
Requires-Dist: numpy
